scrapy_mailgun-0.3.0.dist-info/DESCRIPTION.rst
scrapy_mailgun-0.3.0.dist-info/METADATA
scrapy_mailgun-0.3.0.dist-info/RECORD
scrapy_mailgun-0.3.0.dist-info/WHEEL
scrapy_mailgun-0.3.0.dist-info/metadata.json
scrapy_mailgun-0.3.0.dist-info/top_level.txt
scrapymailgun/__init__.py
scrapymailgun/extensions.py
