Metadata-Version: 2.0
Name: scrapy-mailgun
Version: 0.3.0
Summary: scrapy-mailgun: Hook emails with scrapy.
Home-page: https://github.com/jondot/scrapy-mailgun
Author: Dotan Nahum
Author-email: jondotan@gmail.com
License: Copyright (c) 2017 Dotan Nahum
Requires-Dist: jinja2
Requires-Dist: requests
